howitzer/__init__.py
howitzer/howitzer.py
howitzer/data/__init__.py
howitzer/data/nfl.py
howitzer/enviornments/__init__.py
howitzer/enviornments/sportsbetting.py
howitzer/util/__init__.py
howitzer/util/constants.py
howitzer/util/date.py
howitzer/util/moneymanagement.py
howitzer/util/stats.py
howitzer/util/trading/__init__.py
howitzer/util/trading/indicators.py
howitzer-0.8.0.dist-info/AUTHORS.rst
howitzer-0.8.0.dist-info/LICENSE
howitzer-0.8.0.dist-info/METADATA
howitzer-0.8.0.dist-info/WHEEL
howitzer-0.8.0.dist-info/top_level.txt
howitzer-0.8.0.dist-info/RECORD
